branchnews/__init__.py
branchnews/create.py
branchnews/rename.py
branchnews/util.py
branchnews-0.2.0.dist-info/LICENSE
branchnews-0.2.0.dist-info/METADATA
branchnews-0.2.0.dist-info/WHEEL
branchnews-0.2.0.dist-info/entry_points.txt
branchnews-0.2.0.dist-info/top_level.txt
branchnews-0.2.0.dist-info/RECORD
