Metadata-Version: 2.1
Name: branchnews
Version: 0.2.0
Summary: Branch-based fragment file names for towncrier
Home-page: https://github.com/skieffer/branchnews
License: MIT
Classifier: License :: OSI Approved :: MIT License
Classifier: Programming Language :: Python :: 3
License-File: LICENSE
Requires-Dist: click
Requires-Dist: towncrier >=23.11.0
Provides-Extra: dev
Requires-Dist: pytest ; extra == 'dev'
Requires-Dist: build ; extra == 'dev'
Requires-Dist: twine ; extra == 'dev'
Requires-Dist: invoke ; extra == 'dev'
